muprocdurham/__init__.py
muprocdurham/jupyter.py
muprocdurham/ngram.py
muprocdurham/pcfg.py
muprocdurham/sound.py
muprocdurham/version_check.py
muprocdurham-0.0.7.dist-info/LICENSE
muprocdurham-0.0.7.dist-info/METADATA
muprocdurham-0.0.7.dist-info/WHEEL
muprocdurham-0.0.7.dist-info/top_level.txt
muprocdurham-0.0.7.dist-info/RECORD
