Metadata-Version: 2.2
Name: muprocdurham
Version: 0.0.7
Summary: Python package for the Music Processing lecture and practicals at Durham University
Home-page: https://github.com/MusicComputingDurham/MuProcDurham
Author: Robert Lieck, Eamonn Bell
Classifier: Programming Language :: Python :: 3
Classifier: License :: OSI Approved :: GNU General Public License v3 (GPLv3)
Classifier: Operating System :: OS Independent
Requires-Python: >=3.8
License-File: LICENSE
Requires-Dist: IPython
Requires-Dist: jupyter
Requires-Dist: numpy
Requires-Dist: librosa==0.10.1
Requires-Dist: libfmp==1.2.5
Requires-Dist: ipympl==0.9.3
Requires-Dist: matplotlib<3.10
Requires-Dist: music21
Requires-Dist: umap-learn
Requires-Dist: plotly
Requires-Dist: pygame
Requires-Dist: pitchtypes
Requires-Dist: triangularmap
Requires-Dist: corpusinterface
Dynamic: author
Dynamic: classifier
Dynamic: description
Dynamic: description-content-type
Dynamic: home-page
Dynamic: requires-dist
Dynamic: requires-python
Dynamic: summary
